LICENSE
README.rst
setup.py
datacompress/__init__.py
datacompress.egg-info/PKG-INFO
datacompress.egg-info/SOURCES.txt
datacompress.egg-info/dependency_links.txt
datacompress.egg-info/top_level.txt