Metadata-Version: 2.1
Name: datacompress
Version: 1.8.0
Summary: Comprimir archivos y descomprimir
Home-page: https://gitlab.com/datacommpress
Author: datacompress
Author-email: hola@datacompression.click
License: BSD 2-claus
Platform: UNKNOWN
License-File: LICENSE
